setup.py
anime_images_api/__init__.py
anime_images_api.egg-info/PKG-INFO
anime_images_api.egg-info/SOURCES.txt
anime_images_api.egg-info/dependency_links.txt
anime_images_api.egg-info/requires.txt
anime_images_api.egg-info/top_level.txt