Metadata-Version: 1.1
Name: anime-images-api
Version: 0.0.6
Summary: a wrapper for the anime images api
Home-page: https://discord.com/invite/WhnmkwgtGb
Author: skelly386#1410
Author-email: skellymclane@gmail.com
License: MIT
Keywords: python,image,anime,api,wrapper,py
Platform: UNKNOWN
Classifier: Development Status :: 5 - Production/Stable
Classifier: License :: Free For Educational Use
Classifier: License :: Free For Home Use
Classifier: License :: Free for non-commercial use
Classifier: Natural Language :: English
Classifier: License :: OSI Approved :: MIT License
